fastapi_deploy-0.0.1.dist-info/METADATA
fastapi_deploy-0.0.1.dist-info/WHEEL
fastapi_deploy/__init__.py
fastapi_deploy-0.0.1.dist-info/RECORD
