Metadata-Version: 2.1
Name: fastapi-deploy
Version: 0.0.1
Summary: Default template for PDM package
Author-Email: Sebastián Ramírez <tiangolo@gmail.com>
License: MIT
Requires-Python: >=3.7
